shifter_pandas/__init__.py
shifter_pandas/bp.py
shifter_pandas/ofs.py
shifter_pandas/py.typed
shifter_pandas/wikidata_.py
shifter_pandas/worldbank.py
shifter_pandas-1.0.3.dist-info/LICENSE
shifter_pandas-1.0.3.dist-info/METADATA
shifter_pandas-1.0.3.dist-info/WHEEL
shifter_pandas-1.0.3.dist-info/RECORD
