Metadata-Version: 2.1
Name: shifter-pandas
Version: 1.0.3
Summary: Convert some data into Panda DataFrames
Home-page: https://hub.docker.com/r/sbrunner/shifter-pandas/
License: BSD-2-Clause
Keywords: shifter,pandas
Author: Stéphane Brunner
Author-email: stephane.brunner@gmail.com
Requires-Python: >=3.10
Classifier: Development Status :: 4 - Beta
Classifier: Environment :: Console
Classifier: Intended Audience :: Developers
Classifier: License :: OSI Approved :: BSD License
Classifier: Operating System :: OS Independent
Classifier: Programming Language :: Python
Classifier: Programming Language :: Python :: 3
Classifier: Programming Language :: Python :: 3.10
Classifier: Programming Language :: Python :: 3.11
Classifier: Programming Language :: Python :: 3.12
Classifier: Programming Language :: Python :: 3.13
Classifier: Typing :: Typed
Requires-Dist: certifi
Requires-Dist: idna
Requires-Dist: openpyxl
Requires-Dist: pandas
Requires-Dist: requests
Requires-Dist: toml
Requires-Dist: urllib3
Requires-Dist: wikidata
Project-URL: Repository, https://github.com/sbrunner/shifter-pandas
